polysdk/__init__.py
polysdk/polyclient.py
polysdk/models/__init__.py
polysdk/models/maskeddata.py
polysdk/models/unmaskeddata.py
polysdk-0.0.8.dist-info/LICENSE
polysdk-0.0.8.dist-info/METADATA
polysdk-0.0.8.dist-info/WHEEL
polysdk-0.0.8.dist-info/top_level.txt
polysdk-0.0.8.dist-info/RECORD
