Metadata-Version: 2.1
Name: polysdk
Version: 0.0.8
Summary: Polymer Python SDK.
Home-page: https://github.com/polymerhq/polysdk
Author: Fahad Siddiqui
Author-email: fsid@predictdata.io
License: UNKNOWN
Platform: UNKNOWN
Classifier: Programming Language :: Python :: 3
Classifier: Operating System :: OS Independent
Requires-Python: >=2.7
Requires-Dist: requests (==2.23.0)
